frank/__init__.py
frank-0.0.0.dist-info/AUTHORS.rst
frank-0.0.0.dist-info/LICENSE.txt
frank-0.0.0.dist-info/METADATA
frank-0.0.0.dist-info/WHEEL
frank-0.0.0.dist-info/top_level.txt
frank-0.0.0.dist-info/RECORD
