Metadata-Version: 2.1
Name: frank
Version: 0.0.0
Summary: Frankenstein, the flux reconstructor
Home-page: https://github.com/discsim/frank
Author: Richard Booth, Jeff Jennings, Marco Tazzari
Author-email: jmj51@ast.cam.ac.uk
License: GPLv3
Platform: UNKNOWN
Classifier: Programming Language :: Python :: 3
Requires-Dist: numpy
Requires-Dist: matplotlib
Requires-Dist: scipy
Provides-Extra: docs-build
Requires-Dist: sphinx ; extra == 'docs-build'
Requires-Dist: sphinxcontrib-fulltoc ; extra == 'docs-build'
Requires-Dist: sphinx-rtd-theme ; extra == 'docs-build'
Requires-Dist: nbsphinx ; extra == 'docs-build'
Provides-Extra: test
Requires-Dist: pytest ; extra == 'test'
